LICENSE
MANIFEST.in
README.md
setup.cfg
setup.py
versioneer.py
px4tools/__init__.py
px4tools/_version.py
px4tools/analysis.py
px4tools/logsysid.py
px4tools/mapping.py
px4tools/pandas_monkeypatch.py
px4tools/px42csv.py
px4tools/ulog.py
px4tools.egg-info/PKG-INFO
px4tools.egg-info/SOURCES.txt
px4tools.egg-info/dependency_links.txt
px4tools.egg-info/entry_points.txt
px4tools.egg-info/requires.txt
px4tools.egg-info/top_level.txt
test/__init__.py
test/sdlog2_dump.py
test/test_analysis.py
test/test_px42csv.py